{
	"class" : {
		"RPLAway" : "ls 9/2/1998 22:59",
		"RPLBanList" : "ls 9/2/1998 23:09",
		"RPLChannelModeIs" : "ls 9/2/1998 23:04",
		"RPLEndOfBanList" : "ls 9/2/1998 23:09",
		"RPLEndOfLinks" : "ls 9/2/1998 23:08",
		"RPLEndOfMotd" : "ls 9/2/1998 23:10",
		"RPLEndOfNames" : "ls 9/2/1998 23:08",
		"RPLEndOfWho" : "ls 9/2/1998 23:07",
		"RPLEndOfWhoIs" : "ls 9/2/1998 23:02",
		"RPLEndOfWhoWas" : "ls 9/2/1998 23:03",
		"RPLInviting" : "ls 9/2/1998 23:05",
		"RPLLinks" : "ls 9/2/1998 23:08",
		"RPLList" : "ls 9/2/1998 23:04",
		"RPLListEnd" : "ls 9/2/1998 23:04",
		"RPLListStart" : "ls 9/2/1998 23:04",
		"RPLMotd" : "ls 9/2/1998 23:45",
		"RPLMotd2" : "ls 9/3/1998 18:17",
		"RPLMotdStart" : "ls 9/2/1998 23:09",
		"RPLNamReply" : "ls 9/2/1998 23:08",
		"RPLNoTopic" : "ls 9/2/1998 23:05",
		"RPLNowaway" : "ls 9/2/1998 22:59",
		"RPLSummoning" : "ls 9/2/1998 23:06",
		"RPLTopic" : "ls 9/2/1998 23:05",
		"RPLUnaway" : "ls 9/2/1998 22:59",
		"RPLVersion" : "ls 9/2/1998 23:06",
		"RPLWhoIsIdle" : "ls 9/2/1998 23:02",
		"RPLWhoIsOperator" : "ls 9/2/1998 23:00",
		"RPLWhoIsServer" : "ls 9/2/1998 23:00",
		"RPLWhoIsUser" : "ls 9/2/1998 23:00",
		"RPLWhoReply" : "ls 9/2/1998 23:07",
		"RPLWhoWasUser" : "ls 9/2/1998 23:03",
		"RPLWhoisChannels" : "ls 9/2/1998 23:02",
		"recipient:" : "ls 9/2/1998 18:11",
		"sender:" : "ls 9/2/1998 18:10",
		"sender:recipient:" : "ls 9/2/1998 18:11" },
	"instance" : {
		"matches:" : "ls 9/2/1998 17:42",
		"sender:recipient:" : "ls 9/2/1998 17:41" } }
